[
  {
    "songTime": "2021-12-22T00:01:00",
    "songArtist": "Nirvana",
    "songTitle": "Come As You Are"
  },
  {
    "songTime": "2021-12-22T00:05:00",
    "songArtist": "Matt Maeson",
    "songTitle": "Hallucinogenics"
  },
  {
    "songTime": "2021-12-22T00:08:00",
    "songArtist": "Foals",
    "songTitle": "Wake Me Up"
  },
  {
    "songTime": "2021-12-22T00:12:00",
    "songArtist": "Jet",
    "songTitle": "Are You Gonna Be My Girl"
  },
  {
    "songTime": "2021-12-22T00:15:00",
    "songArtist": "Arkells",
    "songTitle": "Arm In Arm"
  },
  {
    "songTime": "2021-12-22T00:18:00",
    "songArtist": "Smashing Pumpkins",
    "songTitle": "Today"
  },
  {
    "songTime": "2021-12-22T00:21:00",
    "songArtist": "Milky Chance",
    "songTitle": "Colorado"
  },
  {
    "songTime": "2021-12-22T00:24:00",
    "songArtist": "Florence & The Machine",
    "songTitle": "Dog Days Are Over"
  },
  {
    "songTime": "2021-12-22T00:31:00",
    "songArtist": "The Beaches",
    "songTitle": "Blow Up"
  },
  {
    "songTime": "2021-12-22T00:35:00",
    "songArtist": "Imagine Dragons",
    "songTitle": "It's Time"
  },
  {
    "songTime": "2021-12-22T00:39:00",
    "songArtist": "The Royal Foundry",
    "songTitle": "Listen To The Beat"
  },
  {
    "songTime": "2021-12-22T00:45:00",
    "songArtist": "Bastille",
    "songTitle": "Pompeii"
  },
  {
    "songTime": "2021-12-22T00:49:00",
    "songArtist": "SHAED",
    "songTitle": "Trampoline"
  },
  {
    "songTime": "2021-12-22T00:52:00",
    "songArtist": "Tegan and Sara",
    "songTitle": "I'm Not Your Hero"
  },
  {
    "songTime": "2021-12-22T00:56:00",
    "songArtist": "Pearl Jam",
    "songTitle": "Alive"
  },
  {
    "songTime": "2021-12-22T01:02:00",
    "songArtist": "Of Monsters And Men",
    "songTitle": "Alligator"
  },
  {
    "songTime": "2021-12-22T01:05:00",
    "songArtist": "Arcade Fire",
    "songTitle": "Everything Now"
  },
  {
    "songTime": "2021-12-22T01:10:00",
    "songArtist": "Radiohead",
    "songTitle": "Creep"
  },
  {
    "songTime": "2021-12-22T01:14:00",
    "songArtist": "Dear Rouge",
    "songTitle": "Fake Fame"
  },
  {
    "songTime": "2021-12-22T01:18:00",
    "songArtist": "Pixies",
    "songTitle": "Here Comes Your Man"
  },
  {
    "songTime": "2021-12-22T01:21:00",
    "songArtist": "Art d'Ecco",
    "songTitle": "Head Rush"
  },
  {
    "songTime": "2021-12-22T01:24:00",
    "songArtist": "No Doubt",
    "songTitle": "Sunday Morning"
  },
  {
    "songTime": "2021-12-22T01:29:00",
    "songArtist": "Cold War Kids",
    "songTitle": "What You Say"
  },
  {
    "songTime": "2021-12-22T01:33:00",
    "songArtist": "Arkells",
    "songTitle": "Leather Jacket"
  },
  {
    "songTime": "2021-12-22T01:37:00",
    "songArtist": "Alt-J",
    "songTitle": "U&ME"
  },
  {
    "songTime": "2021-12-22T01:40:00",
    "songArtist": "The Killers",
    "songTitle": "Mr. Brightside"
  },
  {
    "songTime": "2021-12-22T01:44:00",
    "songArtist": "Vance Joy",
    "songTitle": "Missing Piece"
  },
  {
    "songTime": "2021-12-22T01:47:00",
    "songArtist": "Foo Fighters",
    "songTitle": "My Hero"
  },
  {
    "songTime": "2021-12-22T01:51:00",
    "songArtist": "Rezz & Metric",
    "songTitle": "Paper Walls"
  },
  {
    "songTime": "2021-12-22T01:55:00",
    "songArtist": "Stone Temple Pilots",
    "songTitle": "Sour Girl"
  },
  {
    "songTime": "2021-12-22T01:59:00",
    "songArtist": "Mother Mother",
    "songTitle": "I Got Love"
  },
  {
    "songTime": "2021-12-22T02:02:00",
    "songArtist": "Nirvana",
    "songTitle": "Smells Like Teen Spirit"
  },
  {
    "songTime": "2021-12-22T02:07:00",
    "songArtist": "Twenty One Pilots",
    "songTitle": "Shy Away"
  },
  {
    "songTime": "2021-12-22T02:10:00",
    "songArtist": "Coin",
    "songTitle": "Chapstick"
  },
  {
    "songTime": "2021-12-22T02:13:00",
    "songArtist": "Gotye",
    "songTitle": "Somebody That I Used to Know"
  },
  {
    "songTime": "2021-12-22T02:17:00",
    "songArtist": "Boy Golden",
    "songTitle": "KD and Lunch Meat"
  },
  {
    "songTime": "2021-12-22T02:21:00",
    "songArtist": "Blind Melon",
    "songTitle": "No Rain"
  },
  {
    "songTime": "2021-12-22T02:25:00",
    "songArtist": "The Lumineers",
    "songTitle": "Brightside"
  },
  {
    "songTime": "2021-12-22T02:28:00",
    "songArtist": "MGMT",
    "songTitle": "Kids"
  },
  {
    "songTime": "2021-12-22T02:34:00",
    "songArtist": "The Beaches",
    "songTitle": "Lame"
  },
  {
    "songTime": "2021-12-22T02:37:00",
    "songArtist": "Fun",
    "songTitle": "We Are Young feat: Janelle Mon\u00e1e"
  },
  {
    "songTime": "2021-12-22T02:41:00",
    "songArtist": "July Talk",
    "songTitle": "I Am Water"
  },
  {
    "songTime": "2021-12-22T02:45:00",
    "songArtist": "Mumford & Sons",
    "songTitle": "Little Lion Man"
  },
  {
    "songTime": "2021-12-22T02:49:00",
    "songArtist": "Meg Myers",
    "songTitle": "The Underground"
  },
  {
    "songTime": "2021-12-22T02:52:00",
    "songArtist": "Sam Roberts",
    "songTitle": "Brother Down"
  },
  {
    "songTime": "2021-12-22T02:57:00",
    "songArtist": "Pulp",
    "songTitle": "Common People"
  },
  {
    "songTime": "2021-12-22T03:02:00",
    "songArtist": "The Black Keys",
    "songTitle": "Shine A Little Light"
  },
  {
    "songTime": "2021-12-22T03:06:00",
    "songArtist": "Dear Rouge",
    "songTitle": "Modern Shakedown"
  },
  {
    "songTime": "2021-12-22T03:09:00",
    "songArtist": "Oasis",
    "songTitle": "Champagne Supernova"
  },
  {
    "songTime": "2021-12-22T03:14:00",
    "songArtist": "Billy Talent",
    "songTitle": "End Of Me (feat. Rivers Cuomo)"
  },
  {
    "songTime": "2021-12-22T03:18:00",
    "songArtist": "New Order",
    "songTitle": "Blue Monday"
  },
  {
    "songTime": "2021-12-22T03:22:00",
    "songArtist": "The Blue Stones",
    "songTitle": "One By One"
  },
  {
    "songTime": "2021-12-22T03:26:00",
    "songArtist": "Cage The Elephant",
    "songTitle": "Ain't No Rest For The Wicked"
  },
  {
    "songTime": "2021-12-22T03:30:00",
    "songArtist": "Nathaniel Rateliff & The Night Sweats",
    "songTitle": "Survivor"
  },
  {
    "songTime": "2021-12-22T03:33:00",
    "songArtist": "City And Colour",
    "songTitle": "The Girl"
  },
  {
    "songTime": "2021-12-22T03:38:00",
    "songArtist": "The War On Drugs",
    "songTitle": "I Don't Live Here Anymore (feat. Lucius)"
  },
  {
    "songTime": "2021-12-22T03:42:00",
    "songArtist": "Keane",
    "songTitle": "Somewhere We Know"
  },
  {
    "songTime": "2021-12-22T03:46:00",
    "songArtist": "Kings Of Leon",
    "songTitle": "The Bandit"
  },
  {
    "songTime": "2021-12-22T03:50:00",
    "songArtist": "Michael Andrews/Gary Jule",
    "songTitle": "Mad World"
  },
  {
    "songTime": "2021-12-22T03:53:00",
    "songArtist": "The Darcys",
    "songTitle": "Running For The Hills"
  },
  {
    "songTime": "2021-12-22T03:56:00",
    "songArtist": "Incubus",
    "songTitle": "Drive"
  },
  {
    "songTime": "2021-12-22T04:00:00",
    "songArtist": "Ruby Waters",
    "songTitle": "Blow"
  },
  {
    "songTime": "2021-12-22T04:03:00",
    "songArtist": "Smashing Pumpkins",
    "songTitle": "-1979-"
  },
  {
    "songTime": "2021-12-22T04:07:00",
    "songArtist": "Bakar",
    "songTitle": "Hell N Back"
  },
  {
    "songTime": "2021-12-22T04:11:00",
    "songArtist": "Foals",
    "songTitle": "Wake Me Up"
  },
  {
    "songTime": "2021-12-22T04:14:00",
    "songArtist": "Green Day",
    "songTitle": "When I Come Around"
  },
  {
    "songTime": "2021-12-22T04:17:00",
    "songArtist": "Arkells",
    "songTitle": "Arm In Arm"
  },
  {
    "songTime": "2021-12-22T04:20:00",
    "songArtist": "The Lumineers",
    "songTitle": "Ophelia"
  },
  {
    "songTime": "2021-12-22T04:23:00",
    "songArtist": "R.E.M.",
    "songTitle": "The One I Love"
  },
  {
    "songTime": "2021-12-22T04:26:00",
    "songArtist": "Milky Chance",
    "songTitle": "Colorado"
  },
  {
    "songTime": "2021-12-22T04:29:00",
    "songArtist": "Jack Johnson",
    "songTitle": "Upside Down"
  },
  {
    "songTime": "2021-12-22T04:32:00",
    "songArtist": "Fatboy Slim",
    "songTitle": "Praise You"
  },
  {
    "songTime": "2021-12-22T04:39:00",
    "songArtist": "Phoenix",
    "songTitle": "1901"
  },
  {
    "songTime": "2021-12-22T04:42:00",
    "songArtist": "The Strumbellas",
    "songTitle": "Greatest Enemy"
  },
  {
    "songTime": "2021-12-22T04:46:00",
    "songArtist": "Sam Fender",
    "songTitle": "Seventeen Going Under"
  },
  {
    "songTime": "2021-12-22T04:51:00",
    "songArtist": "The Black Keys",
    "songTitle": "Little Black Submarines"
  },
  {
    "songTime": "2021-12-22T04:54:00",
    "songArtist": "Vance Joy",
    "songTitle": "Saturday Sun"
  },
  {
    "songTime": "2021-12-22T04:58:00",
    "songArtist": "Mother Mother",
    "songTitle": "Bit By Bit"
  },
  {
    "songTime": "2021-12-22T05:04:00",
    "songArtist": "Meg Myers",
    "songTitle": "Running Up That Hill"
  },
  {
    "songTime": "2021-12-22T05:08:00",
    "songArtist": "Hollerado",
    "songTitle": "Juliette"
  },
  {
    "songTime": "2021-12-22T05:15:00",
    "songArtist": "Of Monsters and Men",
    "songTitle": "Little Talks"
  },
  {
    "songTime": "2021-12-22T05:19:00",
    "songArtist": "The Sheepdogs",
    "songTitle": "Keep On Loving You"
  },
  {
    "songTime": "2021-12-22T05:22:00",
    "songArtist": "Radiohead",
    "songTitle": "Karma Police"
  },
  {
    "songTime": "2021-12-22T05:27:00",
    "songArtist": "Cold War Kids",
    "songTitle": "What You Say"
  },
  {
    "songTime": "2021-12-22T05:30:00",
    "songArtist": "The Zolas",
    "songTitle": "Swooner"
  },
  {
    "songTime": "2021-12-22T05:36:00",
    "songArtist": "Coin",
    "songTitle": "Chapstick"
  },
  {
    "songTime": "2021-12-22T05:40:00",
    "songArtist": "Tame Impala",
    "songTitle": "Elephant"
  },
  {
    "songTime": "2021-12-22T05:44:00",
    "songArtist": "Absofacto",
    "songTitle": "Dissolve"
  },
  {
    "songTime": "2021-12-22T05:50:00",
    "songArtist": "City And Colour",
    "songTitle": "Grand Optimist"
  },
  {
    "songTime": "2021-12-22T05:55:00",
    "songArtist": "New Radicals",
    "songTitle": "You Get What You Give"
  },
  {
    "songTime": "2021-12-22T05:59:00",
    "songArtist": "Depeche Mode",
    "songTitle": "Personal Jesus"
  },
  {
    "songTime": "2021-12-22T06:04:00",
    "songArtist": "Death Cab For Cutie",
    "songTitle": "Gold Rush"
  },
  {
    "songTime": "2021-12-22T06:09:00",
    "songArtist": "Sam Roberts",
    "songTitle": "Hard Road"
  },
  {
    "songTime": "2021-12-22T06:17:00",
    "songArtist": "The Neighbourhood",
    "songTitle": "Sweater Weather"
  },
  {
    "songTime": "2021-12-22T06:21:00",
    "songArtist": "The Lumineers",
    "songTitle": "Brightside"
  },
  {
    "songTime": "2021-12-22T06:25:00",
    "songArtist": "Rezz, Grabbitz",
    "songTitle": "Someone Else"
  },
  {
    "songTime": "2021-12-22T06:29:00",
    "songArtist": "Blur",
    "songTitle": "Song 2"
  },
  {
    "songTime": "2021-12-22T06:32:00",
    "songArtist": "New West",
    "songTitle": "Balenciaga"
  },
  {
    "songTime": "2021-12-22T06:36:00",
    "songArtist": "Garbage",
    "songTitle": "I Think I'm Paranoid"
  },
  {
    "songTime": "2021-12-22T06:39:00",
    "songArtist": "USS",
    "songTitle": "Yin Yang"
  },
  {
    "songTime": "2021-12-22T06:48:00",
    "songArtist": "Black Pumas",
    "songTitle": "Colors"
  },
  {
    "songTime": "2021-12-22T06:51:00",
    "songArtist": "Yukon Blonde",
    "songTitle": "Saturday Night"
  },
  {
    "songTime": "2021-12-22T06:55:00",
    "songArtist": "Kings Of Leon",
    "songTitle": "Use Somebody"
  },
  {
    "songTime": "2021-12-22T06:58:00",
    "songArtist": "Stone Temple Pilots",
    "songTitle": "Sour Girl"
  },
  {
    "songTime": "2021-12-22T07:03:00",
    "songArtist": "Mumford & Sons",
    "songTitle": "The Wolf"
  },
  {
    "songTime": "2021-12-22T07:08:00",
    "songArtist": "Said The Whale",
    "songTitle": "Honey Lungs"
  },
  {
    "songTime": "2021-12-22T07:15:00",
    "songArtist": "Beastie Boys",
    "songTitle": "Sabotage"
  },
  {
    "songTime": "2021-12-22T07:19:00",
    "songArtist": "Boy Golden",
    "songTitle": "KD and Lunch Meat"
  },
  {
    "songTime": "2021-12-22T07:23:00",
    "songArtist": "M83",
    "songTitle": "Midnight City"
  },
  {
    "songTime": "2021-12-22T07:29:00",
    "songArtist": "Nathaniel Rateliff & The Night Sweats",
    "songTitle": "Survivor"
  },
  {
    "songTime": "2021-12-22T07:32:00",
    "songArtist": "Mother Mother",
    "songTitle": "Simply Simple"
  },
  {
    "songTime": "2021-12-22T07:37:00",
    "songArtist": "Chet Faker",
    "songTitle": "Low"
  },
  {
    "songTime": "2021-12-22T07:40:00",
    "songArtist": "Wildlife",
    "songTitle": "Born To Ruin"
  },
  {
    "songTime": "2021-12-22T07:49:00",
    "songArtist": "Imagine Dragons",
    "songTitle": "Demons"
  },
  {
    "songTime": "2021-12-22T07:52:00",
    "songArtist": "The Royal Foundry",
    "songTitle": "okay?"
  },
  {
    "songTime": "2021-12-22T07:56:00",
    "songArtist": "Silversun Pickups",
    "songTitle": "Lazy Eye"
  },
  {
    "songTime": "2021-12-22T08:01:00",
    "songArtist": "Vampire Weekend",
    "songTitle": "Harmony Hall"
  },
  {
    "songTime": "2021-12-22T08:06:00",
    "songArtist": "Sam Roberts",
    "songTitle": "Where Have All The Good People Gone"
  },
  {
    "songTime": "2021-12-22T08:14:00",
    "songArtist": "Lumineers",
    "songTitle": "Cleopatra"
  },
  {
    "songTime": "2021-12-22T08:18:00",
    "songArtist": "Cold War Kids",
    "songTitle": "What You Say"
  },
  {
    "songTime": "2021-12-22T08:22:00",
    "songArtist": "JJ Wilde",
    "songTitle": "Mercy"
  },
  {
    "songTime": "2021-12-22T08:25:00",
    "songArtist": "Of Monsters and Men",
    "songTitle": "Dirty Paws"
  },
  {
    "songTime": "2021-12-22T08:30:00",
    "songArtist": "Arkells",
    "songTitle": "Arm In Arm"
  },
  {
    "songTime": "2021-12-22T08:33:00",
    "songArtist": "Wheatus",
    "songTitle": "Teenage Dirtbag"
  },
  {
    "songTime": "2021-12-22T08:38:00",
    "songArtist": "Sam Fender",
    "songTitle": "Seventeen Going Under"
  },
  {
    "songTime": "2021-12-22T08:47:00",
    "songArtist": "Matt Maeson",
    "songTitle": "Hallucinogenics"
  },
  {
    "songTime": "2021-12-22T08:50:00",
    "songArtist": "The New Pornographers",
    "songTitle": "My Rights Versus Yours"
  },
  {
    "songTime": "2021-12-22T08:54:00",
    "songArtist": "Franz Ferdinand",
    "songTitle": "Take Me Out"
  },
  {
    "songTime": "2021-12-22T08:57:00",
    "songArtist": "Arcade Fire",
    "songTitle": "Creature Comfort"
  },
  {
    "songTime": "2021-12-22T09:01:00",
    "songArtist": "Snow Patrol",
    "songTitle": "Run"
  },
  {
    "songTime": "2021-12-22T09:06:00",
    "songArtist": "Yukon Blonde",
    "songTitle": "Get Precious"
  },
  {
    "songTime": "2021-12-22T09:09:00",
    "songArtist": "Pearl Jam",
    "songTitle": "Daughter"
  },
  {
    "songTime": "2021-12-22T09:13:00",
    "songArtist": "Dear Rouge",
    "songTitle": "Fake Fame"
  },
  {
    "songTime": "2021-12-22T09:17:00",
    "songArtist": "Kings Of Leon",
    "songTitle": "Sex On Fire"
  },
  {
    "songTime": "2021-12-22T09:20:00",
    "songArtist": "Cage The Elephant",
    "songTitle": "Social Cues"
  },
  {
    "songTime": "2021-12-22T09:28:00",
    "songArtist": "City And Colour",
    "songTitle": "Fragile Bird"
  },
  {
    "songTime": "2021-12-22T09:33:00",
    "songArtist": "Milky Chance",
    "songTitle": "Colorado"
  },
  {
    "songTime": "2021-12-22T09:36:00",
    "songArtist": "Serena Ryder",
    "songTitle": "What i Wouldn't Do"
  },
  {
    "songTime": "2021-12-22T09:44:00",
    "songArtist": "July Talk",
    "songTitle": "I Am Water"
  },
  {
    "songTime": "2021-12-22T09:48:00",
    "songArtist": "AWOLNATION",
    "songTitle": "Sail"
  },
  {
    "songTime": "2021-12-22T09:51:00",
    "songArtist": "grandson",
    "songTitle": "Dirty"
  },
  {
    "songTime": "2021-12-22T09:55:00",
    "songArtist": "The 1975",
    "songTitle": "Somebody Else"
  },
  {
    "songTime": "2021-12-22T10:01:00",
    "songArtist": "New West",
    "songTitle": "Balenciaga"
  },
  {
    "songTime": "2021-12-22T10:04:00",
    "songArtist": "Semisonic",
    "songTitle": "Closing Time"
  },
  {
    "songTime": "2021-12-22T10:09:00",
    "songArtist": "Alt-J",
    "songTitle": "U&ME"
  },
  {
    "songTime": "2021-12-22T10:12:00",
    "songArtist": "Tegan And Sara",
    "songTitle": "Hell"
  },
  {
    "songTime": "2021-12-22T10:16:00",
    "songArtist": "Twenty One Pilots",
    "songTitle": "Level Of Concern"
  },
  {
    "songTime": "2021-12-22T10:19:00",
    "songArtist": "Sam Roberts Band",
    "songTitle": "We're All In This Together"
  },
  {
    "songTime": "2021-12-22T10:24:00",
    "songArtist": "The Lumineers",
    "songTitle": "Brightside"
  },
  {
    "songTime": "2021-12-22T10:28:00",
    "songArtist": "Vance Joy",
    "songTitle": "Riptide"
  },
  {
    "songTime": "2021-12-22T10:35:00",
    "songArtist": "Black Pistol Fire",
    "songTitle": "Look Alive"
  },
  {
    "songTime": "2021-12-22T10:39:00",
    "songArtist": "Lorde",
    "songTitle": "Team"
  },
  {
    "songTime": "2021-12-22T10:42:00",
    "songArtist": "Metric",
    "songTitle": "Risk"
  },
  {
    "songTime": "2021-12-22T10:50:00",
    "songArtist": "Cannons",
    "songTitle": "Fire For You"
  },
  {
    "songTime": "2021-12-22T10:54:00",
    "songArtist": "Death Cab For Cutie",
    "songTitle": "You Are A Tourist"
  },
  {
    "songTime": "2021-12-22T10:59:00",
    "songArtist": "The New Pornographers",
    "songTitle": "Moves"
  },
  {
    "songTime": "2021-12-22T11:02:00",
    "songArtist": "The Strokes",
    "songTitle": "Bad Decisions"
  },
  {
    "songTime": "2021-12-22T11:07:00",
    "songArtist": "Dear Rouge",
    "songTitle": "Heard I Had"
  },
  {
    "songTime": "2021-12-22T11:11:00",
    "songArtist": "Cold War Kids",
    "songTitle": "First"
  },
  {
    "songTime": "2021-12-22T11:14:00",
    "songArtist": "Cranberries",
    "songTitle": "Zombie"
  },
  {
    "songTime": "2021-12-22T11:23:00",
    "songArtist": "Bob Moses",
    "songTitle": "Tearing Me Up"
  },
  {
    "songTime": "2021-12-22T11:27:00",
    "songArtist": "Dayglow",
    "songTitle": "Can I Call You Tonight?"
  },
  {
    "songTime": "2021-12-22T11:31:00",
    "songArtist": "Mother Mother",
    "songTitle": "O My Heart"
  },
  {
    "songTime": "2021-12-22T11:38:00",
    "songArtist": "Radiohead",
    "songTitle": "Optimistic"
  },
  {
    "songTime": "2021-12-22T11:43:00",
    "songArtist": "Boy Golden",
    "songTitle": "KD and Lunch Meat"
  },
  {
    "songTime": "2021-12-22T11:47:00",
    "songArtist": "Red Hot Chili Peppers",
    "songTitle": "Can't Stop"
  },
  {
    "songTime": "2021-12-22T11:52:00",
    "songArtist": "Hotel Mira",
    "songTitle": "The Eyes On You"
  },
  {
    "songTime": "2021-12-22T11:56:00",
    "songArtist": "Nirvana",
    "songTitle": "The Man Who Sold The World"
  },
  {
    "songTime": "2021-12-22T11:59:00",
    "songArtist": "The Darcys",
    "songTitle": "Running For The Hills"
  },
  {
    "songTime": "2021-12-22T12:02:00",
    "songArtist": "Arkells",
    "songTitle": "Arm In Arm"
  },
  {
    "songTime": "2021-12-22T12:05:00",
    "songArtist": "No Doubt",
    "songTitle": "Spiderwebs"
  },
  {
    "songTime": "2021-12-22T12:09:00",
    "songArtist": "The War On Drugs",
    "songTitle": "I Don't Live Here Anymore (feat. Lucius)"
  },
  {
    "songTime": "2021-12-22T12:13:00",
    "songArtist": "Japandroids",
    "songTitle": "Near to the Wild Heart of Life"
  },
  {
    "songTime": "2021-12-22T12:18:00",
    "songArtist": "Of Monsters And Men",
    "songTitle": "Visitor"
  },
  {
    "songTime": "2021-12-22T12:22:00",
    "songArtist": "Dan Mangan",
    "songTitle": "Road Regrets"
  },
  {
    "songTime": "2021-12-22T12:26:00",
    "songArtist": "Nathaniel Rateliff & The Night Sweats",
    "songTitle": "Survivor"
  },
  {
    "songTime": "2021-12-22T12:33:00",
    "songArtist": "The Man Who",
    "songTitle": "Natural Villain"
  },
  {
    "songTime": "2021-12-22T12:36:00",
    "songArtist": "Oasis",
    "songTitle": "Don't Look Back In Anger"
  },
  {
    "songTime": "2021-12-22T12:41:00",
    "songArtist": "Our Lady Peace",
    "songTitle": "Stop Making Stupid People Famous"
  },
  {
    "songTime": "2021-12-22T12:45:00",
    "songArtist": "Sam Fender",
    "songTitle": "Seventeen Going Under"
  },
  {
    "songTime": "2021-12-22T12:53:00",
    "songArtist": "Rag'n'Bone Man",
    "songTitle": "Human"
  },
  {
    "songTime": "2021-12-22T12:57:00",
    "songArtist": "Vance Joy",
    "songTitle": "Missing Piece"
  },
  {
    "songTime": "2021-12-22T13:00:00",
    "songArtist": "City and Colour",
    "songTitle": "Wasted Love"
  },
  {
    "songTime": "2021-12-22T13:03:00",
    "songArtist": "Death Cab For Cutie",
    "songTitle": "Northern Lights"
  },
  {
    "songTime": "2021-12-22T13:07:00",
    "songArtist": "Sara Harmer",
    "songTitle": "The Hideout"
  },
  {
    "songTime": "2021-12-22T13:12:00",
    "songArtist": "Cold War Kids",
    "songTitle": "What You Say"
  },
  {
    "songTime": "2021-12-22T13:15:00",
    "songArtist": "Fatboy Slim",
    "songTitle": "The Rockefellar Skank"
  },
  {
    "songTime": "2021-12-22T13:19:00",
    "songArtist": "The Glorious Sons",
    "songTitle": "S.O.S."
  },
  {
    "songTime": "2021-12-22T13:26:00",
    "songArtist": "Rezz & Metric",
    "songTitle": "Paper Walls"
  },
  {
    "songTime": "2021-12-22T13:30:00",
    "songArtist": "Jane's Addiction",
    "songTitle": "Been Caught Stealing"
  },
  {
    "songTime": "2021-12-22T13:34:00",
    "songArtist": "Arkells",
    "songTitle": "Quitting You"
  },
  {
    "songTime": "2021-12-22T13:41:00",
    "songArtist": "Kings Of Leon",
    "songTitle": "The Bandit"
  },
  {
    "songTime": "2021-12-22T13:45:00",
    "songArtist": "Bedouin Soundclash",
    "songTitle": "When The Night Feels My Song"
  },
  {
    "songTime": "2021-12-22T13:49:00",
    "songArtist": "Dear Rouge",
    "songTitle": "Fake Fame"
  },
  {
    "songTime": "2021-12-22T13:52:00",
    "songArtist": "The Revivalists",
    "songTitle": "Wish I Knew You"
  },
  {
    "songTime": "2021-12-22T13:57:00",
    "songArtist": "Mother Mother",
    "songTitle": "Sick Of The Silence"
  },
  {
    "songTime": "2021-12-22T14:00:00",
    "songArtist": "Billy Talent",
    "songTitle": "End Of Me (feat. Rivers Cuomo)"
  },
  {
    "songTime": "2021-12-22T14:04:00",
    "songArtist": "Flora Cash",
    "songTitle": "You're Somebody Else"
  },
  {
    "songTime": "2021-12-22T14:08:00",
    "songArtist": "Foals",
    "songTitle": "Wake Me Up"
  },
  {
    "songTime": "2021-12-22T14:12:00",
    "songArtist": "July Talk",
    "songTitle": "Guns & Ammunition"
  },
  {
    "songTime": "2021-12-22T14:16:00",
    "songArtist": "Girl In Red",
    "songTitle": "Seratonin"
  },
  {
    "songTime": "2021-12-22T14:19:00",
    "songArtist": "Arcade Fire",
    "songTitle": "Keep The Car Running"
  },
  {
    "songTime": "2021-12-22T14:23:00",
    "songArtist": "Milky Chance",
    "songTitle": "Colorado"
  },
  {
    "songTime": "2021-12-22T14:26:00",
    "songArtist": "Red Hot Chili Peppers",
    "songTitle": "Give It Away"
  },
  {
    "songTime": "2021-12-22T14:36:00",
    "songArtist": "Kaleo",
    "songTitle": "Way Down We Go"
  },
  {
    "songTime": "2021-12-22T14:40:00",
    "songArtist": "The Strumbellas",
    "songTitle": "Greatest Enemy"
  },
  {
    "songTime": "2021-12-22T14:44:00",
    "songArtist": "Mumford & Sons",
    "songTitle": "The Cave"
  },
  {
    "songTime": "2021-12-22T14:48:00",
    "songArtist": "Tragically Hip",
    "songTitle": "Wheat Kings"
  },
  {
    "songTime": "2021-12-22T14:56:00",
    "songArtist": "Twenty One Pilots",
    "songTitle": "Shy Away"
  },
  {
    "songTime": "2021-12-22T14:59:00",
    "songArtist": "Sublime",
    "songTitle": "Santaria"
  },
  {
    "songTime": "2021-12-22T15:02:00",
    "songArtist": "Modest Mouse",
    "songTitle": "We Are Between"
  },
  {
    "songTime": "2021-12-22T15:06:00",
    "songArtist": "Dan Mangan",
    "songTitle": "Rows Of Houses"
  },
  {
    "songTime": "2021-12-22T15:11:00",
    "songArtist": "Soundgarden",
    "songTitle": "Black Hole Sun"
  },
  {
    "songTime": "2021-12-22T15:20:00",
    "songArtist": "Big Data",
    "songTitle": "Dangerous"
  },
  {
    "songTime": "2021-12-22T15:25:00",
    "songArtist": "Fake Shark",
    "songTitle": "Loser"
  },
  {
    "songTime": "2021-12-22T15:28:00",
    "songArtist": "The Cure",
    "songTitle": "In Between Days"
  },
  {
    "songTime": "2021-12-22T15:31:00",
    "songArtist": "Chet Faker",
    "songTitle": "Low"
  },
  {
    "songTime": "2021-12-22T15:36:00",
    "songArtist": "The Blue Stones",
    "songTitle": "Let It Ride"
  },
  {
    "songTime": "2021-12-22T15:43:00",
    "songArtist": "Arkells",
    "songTitle": "Arm In Arm"
  },
  {
    "songTime": "2021-12-22T15:47:00",
    "songArtist": "The Killers",
    "songTitle": "Somebody Told Me"
  },
  {
    "songTime": "2021-12-22T15:50:00",
    "songArtist": "The Beaches",
    "songTitle": "Blow Up"
  },
  {
    "songTime": "2021-12-22T15:54:00",
    "songArtist": "Coldplay",
    "songTitle": "Speed Of Sound"
  },
  {
    "songTime": "2021-12-22T15:59:00",
    "songArtist": "Sloan",
    "songTitle": "Money City Maniacs"
  },
  {
    "songTime": "2021-12-22T16:03:00",
    "songArtist": "New West",
    "songTitle": "Balenciaga"
  },
  {
    "songTime": "2021-12-22T16:07:00",
    "songArtist": "Nirvana",
    "songTitle": "Heart Shaped Box"
  },
  {
    "songTime": "2021-12-22T16:12:00",
    "songArtist": "Alt-J",
    "songTitle": "U&ME"
  },
  {
    "songTime": "2021-12-22T16:14:00",
    "songArtist": "Whitehorse",
    "songTitle": "Downtown"
  },
  {
    "songTime": "2021-12-22T16:18:00",
    "songArtist": "Absofacto",
    "songTitle": "Dissolve"
  },
  {
    "songTime": "2021-12-22T16:22:00",
    "songArtist": "Wildlife",
    "songTitle": "Lightning Tent"
  },
  {
    "songTime": "2021-12-22T16:26:00",
    "songArtist": "The Lumineers",
    "songTitle": "Brightside"
  },
  {
    "songTime": "2021-12-22T16:34:00",
    "songArtist": "Arcade Fire",
    "songTitle": "Reflektor"
  },
  {
    "songTime": "2021-12-22T16:39:00",
    "songArtist": "Red Hot Chili Peppers",
    "songTitle": "Under The Bridge"
  },
  {
    "songTime": "2021-12-22T16:44:00",
    "songArtist": "Sam Fender",
    "songTitle": "Seventeen Going Under"
  },
  {
    "songTime": "2021-12-22T16:53:00",
    "songArtist": "Muse",
    "songTitle": "Madness"
  },
  {
    "songTime": "2021-12-22T16:58:00",
    "songArtist": "Tragically Hip",
    "songTitle": "Ahead By A Century"
  },
  {
    "songTime": "2021-12-22T17:02:00",
    "songArtist": "SHAED",
    "songTitle": "Trampoline"
  },
  {
    "songTime": "2021-12-22T17:05:00",
    "songArtist": "Tokyo Police Club",
    "songTitle": "Hot Tonight"
  },
  {
    "songTime": "2021-12-22T17:09:00",
    "songArtist": "Nathaniel Rateliff & The Night Sweats",
    "songTitle": "Survivor"
  },
  {
    "songTime": "2021-12-22T17:13:00",
    "songArtist": "Twenty One Pilots",
    "songTitle": "Stressed Out"
  },
  {
    "songTime": "2021-12-22T17:21:00",
    "songArtist": "The Glorious Sons",
    "songTitle": "Hold Steady"
  },
  {
    "songTime": "2021-12-22T17:23:00",
    "songArtist": "Cage The Elephant",
    "songTitle": "Social Cues"
  },
  {
    "songTime": "2021-12-22T17:28:00",
    "songArtist": "Garbage",
    "songTitle": "Special"
  },
  {
    "songTime": "2021-12-22T17:31:00",
    "songArtist": "The Zolas",
    "songTitle": "Molotov Girls"
  },
  {
    "songTime": "2021-12-22T17:35:00",
    "songArtist": "George Ezra",
    "songTitle": "Budapest"
  },
  {
    "songTime": "2021-12-22T17:42:00",
    "songArtist": "Dear Rouge",
    "songTitle": "Fake Fame"
  },
  {
    "songTime": "2021-12-22T17:46:00",
    "songArtist": "The White Stripes",
    "songTitle": "Seven Nation Army"
  },
  {
    "songTime": "2021-12-22T17:50:00",
    "songArtist": "Oasis",
    "songTitle": "Wonderwall"
  },
  {
    "songTime": "2021-12-22T17:54:00",
    "songArtist": "The Beaches",
    "songTitle": "Lame"
  },
  {
    "songTime": "2021-12-22T17:57:00",
    "songArtist": "No Doubt",
    "songTitle": "It's My Life"
  },
  {
    "songTime": "2021-12-22T18:01:00",
    "songArtist": "The Naked and Famous",
    "songTitle": "Young Blood"
  },
  {
    "songTime": "2021-12-22T18:05:00",
    "songArtist": "Sam Roberts Band",
    "songTitle": "Take Me Away"
  },
  {
    "songTime": "2021-12-22T18:09:00",
    "songArtist": "Milky Chance",
    "songTitle": "Colorado"
  },
  {
    "songTime": "2021-12-22T18:12:00",
    "songArtist": "The Strumbellas",
    "songTitle": "Spirits"
  },
  {
    "songTime": "2021-12-22T18:16:00",
    "songArtist": "Radiohead",
    "songTitle": "Just"
  },
  {
    "songTime": "2021-12-22T18:20:00",
    "songArtist": "Boy Golden",
    "songTitle": "KD and Lunch Meat"
  },
  {
    "songTime": "2021-12-22T18:23:00",
    "songArtist": "Vance Joy",
    "songTitle": "Fire and The Flood"
  },
  {
    "songTime": "2021-12-22T18:31:00",
    "songArtist": "July Talk",
    "songTitle": "I Am Water"
  },
  {
    "songTime": "2021-12-22T18:35:00",
    "songArtist": "Snow Patrol",
    "songTitle": "Chasing Cars"
  },
  {
    "songTime": "2021-12-22T18:40:00",
    "songArtist": "Matt Maeson",
    "songTitle": "Hallucinogenics"
  },
  {
    "songTime": "2021-12-22T18:46:00",
    "songArtist": "The New Pornographers",
    "songTitle": "High Ticket Attractions"
  },
  {
    "songTime": "2021-12-22T18:50:00",
    "songArtist": "The Head and the Heart",
    "songTitle": "Missed Connection"
  },
  {
    "songTime": "2021-12-22T18:53:00",
    "songArtist": "City And Colour",
    "songTitle": "Waiting"
  },
  {
    "songTime": "2021-12-22T18:58:00",
    "songArtist": "Coin",
    "songTitle": "Chapstick"
  },
  {
    "songTime": "2021-12-22T19:01:00",
    "songArtist": "Weezer",
    "songTitle": "All My Favorite Songs"
  },
  {
    "songTime": "2021-12-22T19:05:00",
    "songArtist": "Tegan And Sara",
    "songTitle": "Walking With A Ghost"
  },
  {
    "songTime": "2021-12-22T19:07:00",
    "songArtist": "Billy Talent",
    "songTitle": "End Of Me (feat. Rivers Cuomo)"
  },
  {
    "songTime": "2021-12-22T19:11:00",
    "songArtist": "Twenty One Pilots",
    "songTitle": "My Blood"
  },
  {
    "songTime": "2021-12-22T19:19:00",
    "songArtist": "The Sheepdogs",
    "songTitle": "Keep On Loving You"
  },
  {
    "songTime": "2021-12-22T19:22:00",
    "songArtist": "Cake",
    "songTitle": "Short Skirt Long Jacket"
  },
  {
    "songTime": "2021-12-22T19:25:00",
    "songArtist": "Cold War Kids",
    "songTitle": "What You Say"
  },
  {
    "songTime": "2021-12-22T19:32:00",
    "songArtist": "Dear Rouge",
    "songTitle": "Black To Gold"
  },
  {
    "songTime": "2021-12-22T19:35:00",
    "songArtist": "The War On Drugs",
    "songTitle": "I Don't Live Here Anymore (feat. Lucius)"
  },
  {
    "songTime": "2021-12-22T19:39:00",
    "songArtist": "Red Hot Chili Peppers",
    "songTitle": "Dani California"
  },
  {
    "songTime": "2021-12-22T19:44:00",
    "songArtist": "Bakar",
    "songTitle": "Hell N Back"
  },
  {
    "songTime": "2021-12-22T19:48:00",
    "songArtist": "Metric",
    "songTitle": "Youth Without Youth"
  },
  {
    "songTime": "2021-12-22T19:51:00",
    "songArtist": "Verve",
    "songTitle": "Bitter Sweet Symphony"
  },
  {
    "songTime": "2021-12-22T19:56:00",
    "songArtist": "The Royal Foundry",
    "songTitle": "Listen To The Beat"
  },
  {
    "songTime": "2021-12-22T19:59:00",
    "songArtist": "Violent Femmes",
    "songTitle": "Blister In The Sun"
  },
  {
    "songTime": "2021-12-22T20:02:00",
    "songArtist": "David Gray",
    "songTitle": "Babylon"
  },
  {
    "songTime": "2021-12-22T20:06:00",
    "songArtist": "The Blue Stones",
    "songTitle": "One By One"
  },
  {
    "songTime": "2021-12-22T20:10:00",
    "songArtist": "Coldplay",
    "songTitle": "Clocks"
  },
  {
    "songTime": "2021-12-22T20:15:00",
    "songArtist": "The Lumineers",
    "songTitle": "Brightside"
  },
  {
    "songTime": "2021-12-22T20:19:00",
    "songArtist": "Depeche Mode",
    "songTitle": "People Are People"
  },
  {
    "songTime": "2021-12-22T20:23:00",
    "songArtist": "New West",
    "songTitle": "Balenciaga"
  },
  {
    "songTime": "2021-12-22T20:26:00",
    "songArtist": "Foster The People",
    "songTitle": "Don't Stop (Color On The Walls)"
  },
  {
    "songTime": "2021-12-22T20:33:00",
    "songArtist": "Royal Blood",
    "songTitle": "Trouble's Coming"
  },
  {
    "songTime": "2021-12-22T20:36:00",
    "songArtist": "Stars",
    "songTitle": "Fixed"
  },
  {
    "songTime": "2021-12-22T20:40:00",
    "songArtist": "Sam Fender",
    "songTitle": "Seventeen Going Under"
  },
  {
    "songTime": "2021-12-22T20:48:00",
    "songArtist": "Vance Joy",
    "songTitle": "Missing Piece"
  },
  {
    "songTime": "2021-12-22T20:51:00",
    "songArtist": "Gandharvas",
    "songTitle": "Downtime"
  },
  {
    "songTime": "2021-12-22T20:55:00",
    "songArtist": "Ruby Waters",
    "songTitle": "Blow"
  },
  {
    "songTime": "2021-12-22T20:58:00",
    "songArtist": "Nirvana",
    "songTitle": "All Apologies"
  },
  {
    "songTime": "2021-12-22T21:57:00",
    "songArtist": "Arkells",
    "songTitle": "Arm In Arm"
  },
  {
    "songTime": "2021-12-22T22:00:00",
    "songArtist": "The Royal Foundry",
    "songTitle": "okay?"
  },
  {
    "songTime": "2021-12-22T22:04:00",
    "songArtist": "Gorillaz",
    "songTitle": "Feel Good INC"
  },
  {
    "songTime": "2021-12-22T22:08:00",
    "songArtist": "Cold War Kids",
    "songTitle": "What You Say"
  },
  {
    "songTime": "2021-12-22T22:12:00",
    "songArtist": "Metric",
    "songTitle": "Help I'm Alive"
  },
  {
    "songTime": "2021-12-22T22:15:00",
    "songArtist": "Joy Division",
    "songTitle": "Love Will tear Us Apart"
  },
  {
    "songTime": "2021-12-22T22:19:00",
    "songArtist": "Billy Talent",
    "songTitle": "End Of Me (feat. Rivers Cuomo)"
  },
  {
    "songTime": "2021-12-22T22:23:00",
    "songArtist": "Jack Johnson",
    "songTitle": "Upside Down"
  },
  {
    "songTime": "2021-12-22T22:30:00",
    "songArtist": "The Darcys",
    "songTitle": "Running For The Hills"
  },
  {
    "songTime": "2021-12-22T22:33:00",
    "songArtist": "Smashing Pumpkins",
    "songTitle": "-1979-"
  },
  {
    "songTime": "2021-12-22T22:37:00",
    "songArtist": "Cannons",
    "songTitle": "Fire For You"
  },
  {
    "songTime": "2021-12-22T22:44:00",
    "songArtist": "Dan Mangan",
    "songTitle": "Robots"
  },
  {
    "songTime": "2021-12-22T22:49:00",
    "songArtist": "Matt Maeson",
    "songTitle": "Cringe"
  },
  {
    "songTime": "2021-12-22T22:52:00",
    "songArtist": "Limblifter",
    "songTitle": "Ariel vs Lotus"
  },
  {
    "songTime": "2021-12-22T22:56:00",
    "songArtist": "Foals",
    "songTitle": "Wake Me Up"
  },
  {
    "songTime": "2021-12-22T23:00:00",
    "songArtist": "Vance Joy",
    "songTitle": "Saturday Sun"
  },
  {
    "songTime": "2021-12-22T23:03:00",
    "songArtist": "Dear Rouge",
    "songTitle": "Live Through The Night"
  },
  {
    "songTime": "2021-12-22T23:07:00",
    "songArtist": "Boy Golden",
    "songTitle": "KD and Lunch Meat"
  },
  {
    "songTime": "2021-12-22T23:11:00",
    "songArtist": "Radiohead",
    "songTitle": "Creep"
  },
  {
    "songTime": "2021-12-22T23:18:00",
    "songArtist": "Yukon Blonde",
    "songTitle": "Get Precious"
  },
  {
    "songTime": "2021-12-22T23:21:00",
    "songArtist": "Young The Giant",
    "songTitle": "My Body"
  },
  {
    "songTime": "2021-12-22T23:26:00",
    "songArtist": "The Lumineers",
    "songTitle": "Brightside"
  },
  {
    "songTime": "2021-12-22T23:32:00",
    "songArtist": "Alt-J",
    "songTitle": "U&ME"
  },
  {
    "songTime": "2021-12-22T23:35:00",
    "songArtist": "City and Colour",
    "songTitle": "The Lonely Life"
  },
  {
    "songTime": "2021-12-22T23:40:00",
    "songArtist": "Kings Of Leon",
    "songTitle": "The Bandit"
  },
  {
    "songTime": "2021-12-22T23:44:00",
    "songArtist": "Half Moon Run",
    "songTitle": "Call Me In The Afternoon"
  },
  {
    "songTime": "2021-12-22T23:47:00",
    "songArtist": "Nirvana",
    "songTitle": "Smells Like Teen Spirit"
  },
  {
    "songTime": "2021-12-22T23:52:00",
    "songArtist": "Rezz & Metric",
    "songTitle": "Paper Walls"
  },
  {
    "songTime": "2021-12-22T23:55:00",
    "songArtist": "Jane's Addiction",
    "songTitle": "Jane Says"
  }
]